<?xml version="1.0"?>
<CRates>
  <Date>20110221</Date>
  <Currencies>
    <Currency>
      <ID>AED</ID>
      <Units>1</Units>
      <Rate>0.14100000</Rate>
    </Currency>
    <Currency>
      <ID>AUD</ID>
      <Units>1</Units>
      <Rate>0.52300000</Rate>
    </Currency>
    <Currency>
      <ID>BGN</ID>
      <Units>1</Units>
      <Rate>0.35900000</Rate>
    </Currency>
    <Currency>
      <ID>BYR</ID>
      <Units>1000</Units>
      <Rate>0.17100000</Rate>
    </Currency>
    <Currency>
      <ID>CAD</ID>
      <Units>1</Units>
      <Rate>0.52600000</Rate>
    </Currency>
    <Currency>
      <ID>CHF</ID>
      <Units>1</Units>
      <Rate>0.54400000</Rate>
    </Currency>
    <Currency>
      <ID>CNY</ID>
      <Units>1</Units>
      <Rate>0.07860000</Rate>
    </Currency>
    <Currency>
      <ID>CZK</ID>
      <Units>1</Units>
      <Rate>0.02890000</Rate>
    </Currency>
    <Currency>
      <ID>DKK</ID>
      <Units>1</Units>
      <Rate>0.09430000</Rate>
    </Currency>
    <Currency>
      <ID>EGP</ID>
      <Units>1</Units>
      <Rate>0.08790000</Rate>
    </Currency>
    <Currency>
      <ID>EUR</ID>
      <Units>1</Units>
      <Rate>0.70280400</Rate>
    </Currency>
    <Currency>
      <ID>GBP</ID>
      <Units>1</Units>
      <Rate>0.83600000</Rate>
    </Currency>
    <Currency>
      <ID>HKD</ID>
      <Units>1</Units>
      <Rate>0.06640000</Rate>
    </Currency>
    <Currency>
      <ID>HRK</ID>
      <Units>1</Units>
      <Rate>0.09490000</Rate>
    </Currency>
    <Currency>
      <ID>HUF</ID>
      <Units>100</Units>
      <Rate>0.26100000</Rate>
    </Currency>
    <Currency>
      <ID>ILS</ID>
      <Units>1</Units>
      <Rate>0.14300000</Rate>
    </Currency>
    <Currency>
      <ID>INR</ID>
      <Units>1</Units>
      <Rate>0.01140000</Rate>
    </Currency>
    <Currency>
      <ID>ISK</ID>
      <Units>100</Units>
      <Rate>0.44100000</Rate>
    </Currency>
    <Currency>
      <ID>JPY</ID>
      <Units>100</Units>
      <Rate>0.62100000</Rate>
    </Currency>
    <Currency>
      <ID>KRW</ID>
      <Units>100</Units>
      <Rate>0.04650000</Rate>
    </Currency>
    <Currency>
      <ID>KZT</ID>
      <Units>1000</Units>
      <Rate>3.54000000</Rate>
    </Currency>
    <Currency>
      <ID>LTL</ID>
      <Units>1</Units>
      <Rate>0.20400000</Rate>
    </Currency>
    <Currency>
      <ID>MAD</ID>
      <Units>1</Units>
      <Rate>0.06270000</Rate>
    </Currency>
    <Currency>
      <ID>MDL</ID>
      <Units>1</Units>
      <Rate>0.04290000</Rate>
    </Currency>
    <Currency>
      <ID>NOK</ID>
      <Units>1</Units>
      <Rate>0.09060000</Rate>
    </Currency>
    <Currency>
      <ID>NZD</ID>
      <Units>1</Units>
      <Rate>0.39300000</Rate>
    </Currency>
    <Currency>
      <ID>PLN</ID>
      <Units>1</Units>
      <Rate>0.18000000</Rate>
    </Currency>
    <Currency>
      <ID>RON</ID>
      <Units>1</Units>
      <Rate>0.16500000</Rate>
    </Currency>
    <Currency>
      <ID>RUB</ID>
      <Units>1</Units>
      <Rate>0.01770000</Rate>
    </Currency>
    <Currency>
      <ID>SEK</ID>
      <Units>1</Units>
      <Rate>0.08070000</Rate>
    </Currency>
    <Currency>
      <ID>SGD</ID>
      <Units>1</Units>
      <Rate>0.40500000</Rate>
    </Currency>
    <Currency>
      <ID>TND</ID>
      <Units>1</Units>
      <Rate>0.36300000</Rate>
    </Currency>
    <Currency>
      <ID>TRY</ID>
      <Units>1</Units>
      <Rate>0.32800000</Rate>
    </Currency>
    <Currency>
      <ID>TWD</ID>
      <Units>1</Units>
      <Rate>0.01760000</Rate>
    </Currency>
    <Currency>
      <ID>UAH</ID>
      <Units>1</Units>
      <Rate>0.06500000</Rate>
    </Currency>
    <Currency>
      <ID>USD</ID>
      <Units>1</Units>
      <Rate>0.51700000</Rate>
    </Currency>
    <Currency>
      <ID>UZS</ID>
      <Units>100</Units>
      <Rate>0.03110000</Rate>
    </Currency>
    <Currency>
      <ID>XAU</ID>
      <Units>1</Units>
      <Rate>715.75300000</Rate>
    </Currency>
    <Currency>
      <ID>XDR</ID>
      <Units>1</Units>
      <Rate>0.80500000</Rate>
    </Currency>
    <Currency>
      <ID>ZAR</ID>
      <Units>1</Units>
      <Rate>0.07200000</Rate>
    </Currency>
  </Currencies>
</CRates>
